{
  "id": "002",
  "firstName": "",
  "lastName": "",
  "age": "",
  "languages": [
    {
      "language": ""
    }
  ],
  "school": "",
  "license": "No License",
  "phoneNum": "",
  "mail": "",
  "suburb": "",
  "city": "",
  "country": "New Zealand",
  "statement": "",
  "employment": [
    {
      "jobCompany": "",
      "startDate": "",
      "endDate": "",
      "title": "",
      "jobDescription": ""
    }
  ],
  "volunteering": [
    {
      "volCompany": "",
      "volStartDate": "",
      "volEndDate": "",
      "volTitle": "",
      "volDescription": ""
    }
  ],
  "education": [
    {
      "schoolYear": "",
      "schoolYearGrade": "",
      "subjects": [
        {
          "subject": "",
          "grade": ""
        },
        {
          "subject": "",
          "grade": ""
        },
        {
          "subject": "",
          "grade": ""
        },
        {
          "subject": "",
          "grade": ""
        },
        {
          "subject": "",
          "grade": ""
        }
      ]
    }
  ],
  "qualities": [
    {
      "quality": "Accurate"
    },
    {
      "quality": "Adaptable"
    },
    {
      "quality": "Amiable"
    },
    {
      "quality": "Analytical"
    }
  ],
  "submit": "save",
  "awards": [
    {
      "awardYear": "",
      "award": ""
    }
  ],
  "extracur": [
    {
      "extracurYear": "",
      "activity": ""
    }
  ],
  "referees": [
    {
      "refName": "",
      "refPosition": "",
      "refEmail": "",
      "refNum": ""
    }
  ]
}